{
  "v1": {
    "options": [
      {
        "bundle": [
          {
            "file": "build/bundle/rust_app.bundle.zip"
          }
        ],
        "runtime_config": {
          "sys_params": {
            "wasm_memory_size": 50331648,
            "memory_reservations": {
              "low": {
                "runtime": 17408,
                "rhi": 262144,
                "render_device": 2167336,
                "canvas": 14680064,
                "canvas_font_scratchpad": 2097152,
                "cncbus": 2097152,
                "curl": 2097152,
                "json_deflate": 10485760,
                "default_thread_pool": 262144,
                "http2": 2097152,
                "httpx": 2097152
              },
              "high": {
                "canvas": 31457280
              }
            },
            "guard_page_mode": "disabled",
            "adk_websocket": {
              "backend": "http2",
              "websocket_config": {
                "ping_timeout": 10000,
                "no_activity_wait_period": 50000,
                "max_handshake_timeout": 60000,
                "max_receivable_message_size": 1048576,
                "receive_buffer_size": 2048,
                "send_buffer_size": 4096,
                "header_buffer_size": 4096,
                "maximum_redirects": 10
              }
            }
          }
        }
      }
    ]
  }
}
